pyffuf/banner.py
pyffuf/checker.py
pyffuf/main.py
pyffuf/wordcounter.py
pyffuf-0.4.dist-info/LICENSE
pyffuf-0.4.dist-info/METADATA
pyffuf-0.4.dist-info/WHEEL
pyffuf-0.4.dist-info/entry_points.txt
pyffuf-0.4.dist-info/top_level.txt
pyffuf-0.4.dist-info/RECORD
