Metadata-Version: 2.1
Name: pyffuf
Version: 0.4
Summary: Simple and fast web fuzzer written in python.
Home-page: https://github.com/ScRiPt1337/pyffuf
Author: script1337
Author-email: anon42237@gmail.com
License: MIT
Platform: UNKNOWN
Classifier: License :: OSI Approved :: MIT License
Classifier: Programming Language :: Python :: 3
Classifier: Programming Language :: Python :: 3.8
Requires-Dist: aiohttp
Requires-Dist: argparse
Requires-Dist: asyncio
Requires-Dist: beautifulsoup4
Requires-Dist: clint
Requires-Dist: datetime
